loopster/__init__.py
loopster/exceptions.py
loopster/sig.py
loopster/states.py
loopster/units.py
loopster/utils.py
loopster/version.py
loopster/common/__init__.py
loopster/common/exc.py
loopster/common/obj.py
loopster/hubs/__init__.py
loopster/hubs/base.py
loopster/hubs/process.py
loopster/hubs/controllers/__init__.py
loopster/hubs/controllers/base.py
loopster/hubs/controllers/force_state.py
loopster/hubs/controllers/panic.py
loopster/hubs/drivers/__init__.py
loopster/hubs/drivers/base.py
loopster/hubs/drivers/process.py
loopster/services/__init__.py
loopster/services/base.py
loopster/services/base_nested.py
loopster/services/bjoern.py
loopster/services/multi_mysql.py
loopster/services/mysql.py
loopster/services/softirq.py
loopster/services/softirq_etcd.py
loopster/tests/__init__.py
loopster/tests/functional/__init__.py
loopster/tests/functional/hubs/__init__.py
loopster/tests/functional/hubs/drivers/__init__.py
loopster/tests/functional/hubs/drivers/test_process.py
loopster/tests/functional/services/__init__.py
loopster/tests/functional/services/test_softirq.py
loopster/tests/unit/__init__.py
loopster/tests/unit/hubs/__init__.py
loopster/tests/unit/hubs/test_base.py
loopster/tests/unit/hubs/controllers/__init__.py
loopster/tests/unit/hubs/controllers/test_panic.py
loopster/tests/unit/hubs/drivers/__init__.py
loopster/tests/unit/hubs/drivers/test_process.py
loopster/tests/unit/services/__init__.py
loopster/tests/unit/services/test_base.py
loopster/tests/unit/services/test_multi_mysql.py
loopster/tests/unit/services/test_mysql.py
loopster/tests/unit/services/test_softirq.py
loopster/tests/unit/watchdogs/__init__.py
loopster/tests/unit/watchdogs/test_base.py
loopster/tests/unit/watchdogs/test_etcd.py
loopster/tests/unit/watchdogs/test_factory.py
loopster/watchdogs/__init__.py
loopster/watchdogs/base.py
loopster/watchdogs/etcd.py
loopster/watchdogs/exceptions.py
loopster/watchdogs/factory.py
loopster-2.14.4.dist-info/licenses/AUTHORS
loopster-2.14.4.dist-info/licenses/LICENSE
loopster-2.14.4.dist-info/METADATA
loopster-2.14.4.dist-info/WHEEL
loopster-2.14.4.dist-info/pbr.json
loopster-2.14.4.dist-info/top_level.txt
loopster-2.14.4.dist-info/RECORD
