Metadata-Version: 2.4
Name: loopster
Version: 2.14.4
Summary: Service library
Home-page: https://github.com/vktechdev/loopster
Author: VK Tech
Author-email: digital.tech@corp.mail.ru
Classifier: Intended Audience :: Developers
Classifier: License :: OSI Approved :: Apache Software License
Classifier: Operating System :: POSIX :: Linux
Classifier: Programming Language :: Python
Classifier: Programming Language :: Python :: 2
Classifier: Programming Language :: Python :: 2.7
Classifier: Programming Language :: Python :: 3
Classifier: Programming Language :: Python :: 3.6
Classifier: Programming Language :: Python :: 3.8
License-File: LICENSE
License-File: AUTHORS
Requires-Dist: pbr<=5.8.1,>=1.10.0
Requires-Dist: six<=1.16.0,>=1.10.0
Requires-Dist: enum34<=1.1.10,>=1.1.6; python_version < "3.4"
Provides-Extra: mysqlwrapper
Requires-Dist: restalchemy>=5.1.0; extra == "mysqlwrapper"
Provides-Extra: bjoernsvc
Requires-Dist: bjoern==3.1.0; extra == "bjoernsvc"
Provides-Extra: etcdguard
Requires-Dist: httpetcd<1.0.0,>=0.3.3; extra == "etcdguard"
Provides-Extra: test
Requires-Dist: hacking<3; extra == "test"
Requires-Dist: pytest<9.0.0,>=8.0.0; extra == "test"
Requires-Dist: pytest-timer<2.0.0,>=1.0.0; extra == "test"
Requires-Dist: pytest-cov<7.0.0,>=5.0.0; extra == "test"
Requires-Dist: coverage<6,>=3.6; extra == "test"
Requires-Dist: mock<3.0.5,>=1.0.1; extra == "test"
Requires-Dist: httpetcd<1.0.0,>=0.3.3; extra == "test"
Requires-Dist: restalchemy>=4.9.4; extra == "test"
Requires-Dist: flake8>=3.8.4; extra == "test"
Dynamic: author
Dynamic: author-email
Dynamic: classifier
Dynamic: description
Dynamic: home-page
Dynamic: license-file
Dynamic: provides-extra
Dynamic: requires-dist
Dynamic: summary
